example/__init__.py
example/example.py
src/__init__.py
src/eukfindertest.py
eukfindertest2-1.0.1.dist-info/LICENCE.txt
eukfindertest2-1.0.1.dist-info/METADATA
eukfindertest2-1.0.1.dist-info/WHEEL
eukfindertest2-1.0.1.dist-info/top_level.txt
eukfindertest2-1.0.1.dist-info/RECORD
