Metadata-Version: 2.1
Name: eukfindertest2
Version: 1.0.1
Summary: A small demo package
Home-page: https://github.com/dzhao2019/eukfindertest
Author: dzhao
Author-email: dandan.tanny.zhao@email.com
Classifier: Programming Language :: Python :: 3
Classifier: License :: OSI Approved :: MIT License
Classifier: Operating System :: OS Independent
License-File: LICENCE.txt
Requires-Dist: ete3
Requires-Dist: pandas
Requires-Dist: joblib
Requires-Dist: numpy
Requires-Dist: pyqt5
